flightgear_python/__init__.py
flightgear_python/ctrls_v27.py
flightgear_python/fdm_v24.py
flightgear_python/fdm_v25.py
flightgear_python/fg_if.py
flightgear_python/fg_util.py
flightgear_python/general_util.py
flightgear_python/gui_v8.py
flightgear_python-2.0.3.dist-info/LICENSE
flightgear_python-2.0.3.dist-info/METADATA
flightgear_python-2.0.3.dist-info/WHEEL
flightgear_python-2.0.3.dist-info/RECORD
