Metadata-Version: 2.1
Name: flightgear_python
Version: 2.0.3
Summary: Interface for FlightGear network connections
License: MIT
Author: Julianne Swinoga
Author-email: julianneswinoga@gmail.com
Requires-Python: >=3.8.1,<4.0.0
Classifier: License :: OSI Approved :: MIT License
Classifier: Programming Language :: Python :: 3
Classifier: Programming Language :: Python :: 3.9
Classifier: Programming Language :: Python :: 3.10
Classifier: Programming Language :: Python :: 3.11
Classifier: Programming Language :: Python :: 3.12
Classifier: Programming Language :: Python :: 3.13
Requires-Dist: construct (>=2.10,<3.0)
Requires-Dist: multiprocess (>=0.70,<0.71)
Requires-Dist: requests (>=2.32,<3.0)
Project-URL: Bug Tracker, https://github.com/julianneswinoga/flightgear-python/issues
Project-URL: Documentation, https://flightgear-python.readthedocs.io/en/latest
Project-URL: Repository, https://github.com/julianneswinoga/flightgear-python
